{
    "trial_type": "imbalanced",
    "method": "naive",
    "dataset": "MNIST",
    "total_samples": 4000,
    "majority_class": 4,
    "minority_class": 9,
    "minority_prop_of_majority": 0.5,
    "seed": 0,
    "train_dataloader_kwargs":
    {
        "batch_size": 100,
        "shuffle": true
    },
    "eval_dataloader_kwargs":
    {
        "batch_size": 100,
        "shuffle": false
    },
    "clean_dataloader_kwargs":
    {
        "batch_size": 100,
        "shuffle": true
    },
    "clean_samples_per_class": 10,
    "val_samples_per_class": 100,
    "model_constructor": "LeNet5",
    "model_constructor_kwargs":
    {
        "overparameterize": false
    },
    "loss_fn_constructor": "CrossEntropyLoss",
    "loss_fn_constructor_kwargs": {},
    "optimizer_constructor": "Adam",
    "optimizer_constructor_kwargs": {},
    "num_epochs": 0,
    "device": "cuda",
    "eval_initial_performance": true,
    "pretrain_epochs": 0,
    "finetune_epochs": 10
}